<PAMDataset>
  <Metadata>
    <MDI key="long_name">ID</MDI>
    <MDI key="name">ID</MDI>
  </Metadata>
  <PAMRasterBand band="1">
    <Description>ID</Description>
    <Metadata>
      <MDI key="STATISTICS_MAXIMUM">4.8542306607303</MDI>
      <MDI key="STATISTICS_MEAN">3.2597082244605</MDI>
      <MDI key="STATISTICS_MINIMUM">2.0796153381324</MDI>
      <MDI key="STATISTICS_STDDEV">0.58603926104084</MDI>
      <MDI key="STATISTICS_VALID_PERCENT">10.6</MDI>
    </Metadata>
  </PAMRasterBand>
</PAMDataset>
